being/__init__.py
being/__main__.py
being/awakening.py
being/backends.py
being/behavior.py
being/behavior_tree.py
being/being.py
being/bitmagic.py
being/block.py
being/blocks.py
being/choreo.py
being/clock.py
being/config.py
being/configs.py
being/configuration.py
being/connectables.py
being/constants.py
being/content.py
being/curve.py
being/error.py
being/execution.py
being/graph.py
being/kinematics.py
being/logging.py
being/math.py
being/motion_player.py
being/motor.py
being/networking.py
being/pacemaker.py
being/params.py
being/plotting.py
being/pubsub.py
being/resources.py
being/rpi_gpio.py
being/sensors.py
being/serialization.py
being/spline.py
being/typing.py
being/utils.py
being/can/__init__.py
being/can/cia_301.py
being/can/cia_402.py
being/can/definitions.py
being/can/nmt.py
being/can/pcan_darwin_patch.py
being/can/eds_files/MCLM3002P-CO.eds
being/can/eds_files/maxon_EPOS4_50-5.eds
being/can/eds_files/pathos_stepper_controller.eds
being/motors/__init__.py
being/motors/blocks.py
being/motors/controllers.py
being/motors/definitions.py
being/motors/homing.py
being/motors/motors.py
being/motors/vendor.py
being/web/__init__.py
being/web/api.py
being/web/responses.py
being/web/server.py
being/web/web_socket.py
being/web/static/.DS_Store
being/web/static/android-chrome-192x192.png
being/web/static/android-chrome-512x512.png
being/web/static/apple-touch-icon.png
being/web/static/components.js
being/web/static/favicon-16x16.png
being/web/static/favicon-32x32.png
being/web/static/favicon.ico
being/web/static/index.html
being/web/static/web-socket-test.html
being/web/static/components/.DS_Store
being/web/static/components/index.js
being/web/static/components/plotter.js
being/web/static/components/behavior/.behavior.css.swp
being/web/static/components/behavior/.behavior.js.swp
being/web/static/components/behavior/.index.js.swp
being/web/static/components/behavior/behavior.css
being/web/static/components/behavior/behavior.js
being-1.0.2.dist-info/LICENSE
being-1.0.2.dist-info/METADATA
being-1.0.2.dist-info/WHEEL
being-1.0.2.dist-info/top_level.txt
being-1.0.2.dist-info/RECORD
