Metadata-Version: 2.1
Name: being
Version: 1.0.2
Summary: Robotic core for the PATHOS project.
Home-page: https://github.com/rauc-lab/being
Author: Alexander Theler
License: MIT
Project-URL: Documentation, https://being.readthedocs.io/en/latest/
Project-URL: PyPi, https://pypi.org/project/being/
Project-URL: Source, https://github.com/rauc-lab/being
Project-URL: Tracker, https://github.com/rauc-lab/being/issues
Project-URL: RAUC, https://asl.ethz.ch/research/rauc.html
Keywords: Poetic animatronics robotic framework
Platform: Darwin
Platform: Linux
Classifier: Development Status :: 4 - Beta
Classifier: Environment :: Console
Classifier: Environment :: MacOS X
Classifier: Environment :: Other Environment
Classifier: Environment :: Web Environment
Classifier: Framework :: Robot Framework
Classifier: Framework :: Robot Framework :: Library
Classifier: Framework :: Robot Framework :: Tool
Classifier: Framework :: Sphinx
Classifier: Framework :: aiohttp
Classifier: Intended Audience :: Developers
Classifier: Intended Audience :: Education
Classifier: Intended Audience :: End Users/Desktop
Classifier: Intended Audience :: Information Technology
Classifier: Intended Audience :: Other Audience
Classifier: Intended Audience :: Science/Research
Classifier: License :: OSI Approved :: MIT License
Classifier: Natural Language :: English
Classifier: Operating System :: MacOS
Classifier: Operating System :: OS Independent
Classifier: Operating System :: POSIX
Classifier: Operating System :: POSIX :: Linux
Classifier: Operating System :: POSIX :: Other
Classifier: Operating System :: Unix
Classifier: Programming Language :: JavaScript
Classifier: Programming Language :: Python :: 3
Classifier: Programming Language :: Python :: 3 :: Only
Classifier: Programming Language :: Python :: 3.8
Classifier: Programming Language :: Python :: 3.9
Classifier: Programming Language :: Python :: 3.10
Classifier: Programming Language :: Python :: 3.11
Classifier: Programming Language :: Python :: Implementation :: CPython
Classifier: Topic :: Artistic Software
Classifier: Topic :: Communications
Classifier: Topic :: Education
Classifier: Topic :: Games/Entertainment
Classifier: Topic :: Home Automation
Classifier: Topic :: Multimedia
Classifier: Topic :: Multimedia :: Graphics
Classifier: Topic :: Multimedia :: Graphics :: Editors
Classifier: Topic :: Multimedia :: Sound/Audio
Classifier: Topic :: Multimedia :: Sound/Audio :: Analysis
Classifier: Topic :: Multimedia :: Sound/Audio :: Capture/Recording
Classifier: Topic :: Other/Nonlisted Topic
Classifier: Topic :: Scientific/Engineering
Classifier: Topic :: Scientific/Engineering :: Human Machine Interfaces
Classifier: Topic :: Software Development
Classifier: Topic :: Software Development :: Libraries
Classifier: Topic :: Software Development :: Libraries :: Application Frameworks
Classifier: Topic :: Software Development :: Libraries :: Python Modules
Classifier: Topic :: Software Development :: User Interfaces
Classifier: Topic :: Software Development :: Widget Sets
Classifier: Topic :: System
Classifier: Topic :: System :: Hardware
Classifier: Topic :: System :: Networking
Classifier: Topic :: Utilities
License-File: LICENSE
Requires-Dist: setuptools
Requires-Dist: numpy
Requires-Dist: scipy
Requires-Dist: matplotlib
Requires-Dist: python-can
Requires-Dist: canopen
Requires-Dist: aiohttp (<=3.7.4,>=3.7.0)
Requires-Dist: jinja2 (>=3.0.0)
Requires-Dist: aiohttp-jinja2
Requires-Dist: ruamel.yaml
Requires-Dist: tomlkit
Requires-Dist: configobj
Provides-Extra: audio
Requires-Dist: PyAudio ; extra == 'audio'
Provides-Extra: rpi
Requires-Dist: RPi.GPIO ; extra == 'rpi'
